benchmarks/__init__.py
benchmarks/datasets.py
benchmarks/timer.py
benchmarks/operators/__init__.py
benchmarks/operators/run.py
benchmarks/operators/score.py
benchmarks/operators/train.py
benchmarks/trees/__init__.py
benchmarks/trees/metrics.py
benchmarks/trees/run.py
benchmarks/trees/score.py
benchmarks/trees/train.py
hummingbird/__init__.py
hummingbird/ml/__init__.py
hummingbird/ml/_executor.py
hummingbird/ml/_parse.py
hummingbird/ml/_topology.py
hummingbird/ml/_utils.py
hummingbird/ml/convert.py
hummingbird/ml/exceptions.py
hummingbird/ml/supported.py
hummingbird/ml/containers/__init__.py
hummingbird/ml/containers/_input_containers.py
hummingbird/ml/containers/_sklearn_api_containers.py
hummingbird/ml/containers/batch_container.py
hummingbird/ml/containers/sklearn/__init__.py
hummingbird/ml/containers/sklearn/onnx_containers.py
hummingbird/ml/containers/sklearn/pytorch_containers.py
hummingbird/ml/containers/sklearn/tvm_containers.py
hummingbird/ml/operator_converters/__init__.py
hummingbird/ml/operator_converters/_array_feature_extractor_implementations.py
hummingbird/ml/operator_converters/_decomposition_implementations.py
hummingbird/ml/operator_converters/_discretizer_implementations.py
hummingbird/ml/operator_converters/_gbdt_commons.py
hummingbird/ml/operator_converters/_imputer_implementations.py
hummingbird/ml/operator_converters/_kneighbors_implementations.py
hummingbird/ml/operator_converters/_label_encoder_implementations.py
hummingbird/ml/operator_converters/_linear_implementations.py
hummingbird/ml/operator_converters/_mlp_implementations.py
hummingbird/ml/operator_converters/_nb_implementations.py
hummingbird/ml/operator_converters/_normalizer_implementations.py
hummingbird/ml/operator_converters/_one_hot_encoder_implementations.py
hummingbird/ml/operator_converters/_physical_operator.py
hummingbird/ml/operator_converters/_pipeline_implementations.py
hummingbird/ml/operator_converters/_scaler_implementations.py
concrete_ml_extensions_hb-0.4.2.2.dist-info/LICENSE
concrete_ml_extensions_hb-0.4.2.2.dist-info/METADATA
concrete_ml_extensions_hb-0.4.2.2.dist-info/NOTICE
concrete_ml_extensions_hb-0.4.2.2.dist-info/WHEEL
concrete_ml_extensions_hb-0.4.2.2.dist-info/top_level.txt
concrete_ml_extensions_hb-0.4.2.2.dist-info/RECORD
