Metadata-Version: 2.1
Name: concrete-ml-extensions-hb
Version: 0.4.2.2
Summary: Convert trained traditional machine learning models into tensor computations
Home-page: https://github.com/zama-ai/hummingbird
License: MIT License
Platform: UNKNOWN
Classifier: Environment :: Console
Classifier: Intended Audience :: Developers
Classifier: Programming Language :: Python
Classifier: Operating System :: OS Independent
Classifier: License :: OSI Approved :: MIT License
Requires-Python: >=3.6
License-File: LICENSE
License-File: NOTICE
Requires-Dist: numpy (>=1.15)
Requires-Dist: onnxconverter-common (>=1.6.0)
Requires-Dist: scipy
Requires-Dist: scikit-learn (>=0.21.3)
Requires-Dist: torch (>=1.4)
Requires-Dist: psutil
Requires-Dist: dill
Provides-Extra: benchmark
Requires-Dist: onnxruntime (>=1.0.0) ; extra == 'benchmark'
Requires-Dist: onnxmltools (>=1.6.0) ; extra == 'benchmark'
Requires-Dist: skl2onnx (>=1.7.0) ; extra == 'benchmark'
Requires-Dist: xgboost (>=0.90) ; extra == 'benchmark'
Requires-Dist: lightgbm (>=2.2) ; extra == 'benchmark'
Requires-Dist: prophet (==1.0.1) ; extra == 'benchmark'
Requires-Dist: memory-profiler ; extra == 'benchmark'
Requires-Dist: psutil ; extra == 'benchmark'
Provides-Extra: extra
Requires-Dist: xgboost (>=0.90) ; extra == 'extra'
Requires-Dist: lightgbm (>=2.2) ; extra == 'extra'
Requires-Dist: prophet (==1.0.1) ; extra == 'extra'
Provides-Extra: onnx
Requires-Dist: onnxruntime (>=1.0.0) ; extra == 'onnx'
Requires-Dist: onnxmltools (>=1.6.0) ; extra == 'onnx'
Requires-Dist: skl2onnx (>=1.7.0) ; extra == 'onnx'
Provides-Extra: sparkml
Requires-Dist: pyspark (<3.1.2,>=2.4.4) ; extra == 'sparkml'
Requires-Dist: pyarrow (>1.0) ; extra == 'sparkml'
Provides-Extra: tests
Requires-Dist: flake8 ; extra == 'tests'
Requires-Dist: pytest ; extra == 'tests'
Requires-Dist: coverage ; extra == 'tests'
Requires-Dist: pre-commit ; extra == 'tests'
